<?xml version="1.0" encoding="UTF-8"?>
<metadata xml:lang="en"><Esri><CreaDate>20150604</CreaDate><CreaTime>13495300</CreaTime><ArcGISFormat>1.0</ArcGISFormat><ArcGISstyle>FGDC CSDGM Metadata</ArcGISstyle><SyncOnce>FALSE</SyncOnce><DataProperties><lineage><Process ToolSource="c:\program files (x86)\arcgis\desktop10.1\ArcToolbox\Toolboxes\Data Management Tools.tbx\CalculateField" Date="20140616" Time="150017">CalculateField RideScore OBDTEXT "&gt; 2 miles" VB #</Process><Process ToolSource="c:\program files (x86)\arcgis\desktop10.1\ArcToolbox\Toolboxes\Data Management Tools.tbx\CalculateField" Date="20140616" Time="150106">CalculateField RideScore OBDTEXT "&lt;= 1/4 mi" VB #</Process><Process ToolSource="c:\program files (x86)\arcgis\desktop10.1\ArcToolbox\Toolboxes\Data Management Tools.tbx\CalculateField" Date="20140616" Time="150127">CalculateField RideScore OBDTEXT "&lt;= 1/4 mile" VB #</Process><Process ToolSource="c:\program files (x86)\arcgis\desktop10.1\ArcToolbox\Toolboxes\Data Management Tools.tbx\CalculateField" Date="20140616" Time="150154">CalculateField RideScore OBDTEXT "1 mile to 2 miles" VB #</Process><Process ToolSource="c:\program files (x86)\arcgis\desktop10.1\ArcToolbox\Toolboxes\Data Management Tools.tbx\CalculateField" Date="20140616" Time="151418">CalculateField RideScore WLKTEXT "1/2 mi&gt;=1 mi" VB #</Process><Process ToolSource="c:\program files (x86)\arcgis\desktop10.1\ArcToolbox\Toolboxes\Data Management Tools.tbx\CalculateField" Date="20140616" Time="151437">CalculateField RideScore WLKTEXT "1/2 mi &gt;=1 mi" VB #</Process><Process ToolSource="c:\program files (x86)\arcgis\desktop10.1\ArcToolbox\Toolboxes\Data Management Tools.tbx\CalculateField" Date="20140616" Time="151454">CalculateField RideScore WLKTEXT "1/4 mi &gt;=1/2 mi" VB #</Process><Process ToolSource="c:\program files (x86)\arcgis\desktop10.1\ArcToolbox\Toolboxes\Data Management Tools.tbx\CalculateField" Date="20140616" Time="151658">CalculateField RideScore CTNTEXT "&gt; 1 mile" VB #</Process><Process ToolSource="c:\program files (x86)\arcgis\desktop10.1\ArcToolbox\Toolboxes\Data Management Tools.tbx\CalculateField" Date="20140616" Time="151718">CalculateField RideScore CTNTEXT "On/Adjacent" VB #</Process><Process ToolSource="c:\program files (x86)\arcgis\desktop10.1\ArcToolbox\Toolboxes\Data Management Tools.tbx\CalculateField" Date="20140616" Time="151827">CalculateField RideScore CTNTEXT "1/2 mile &gt;= 1 mile" VB #</Process><Process ToolSource="c:\program files (x86)\arcgis\desktop10.1\ArcToolbox\Toolboxes\Data Management Tools.tbx\CalculateField" Date="20140616" Time="151931">CalculateField RideScore WLKTEXT "&lt;= 1/4 mile" VB #</Process><Process ToolSource="c:\program files (x86)\arcgis\desktop10.1\ArcToolbox\Toolboxes\Data Management Tools.tbx\CalculateField" Date="20140616" Time="151954">CalculateField RideScore WLKTEXT "1 mile &gt;=2 mile" VB #</Process><Process ToolSource="c:\program files (x86)\arcgis\desktop10.1\ArcToolbox\Toolboxes\Data Management Tools.tbx\CalculateField" Date="20140616" Time="152012">CalculateField RideScore WLKTEXT "1/2 mile &gt;=1 mile" VB #</Process><Process ToolSource="c:\program files (x86)\arcgis\desktop10.1\ArcToolbox\Toolboxes\Data Management Tools.tbx\CalculateField" Date="20140616" Time="152036">CalculateField RideScore WLKTEXT "1/4 mile &gt;=1/2 mile" VB #</Process><Process ToolSource="c:\program files (x86)\arcgis\desktop10.1\ArcToolbox\Toolboxes\Data Management Tools.tbx\CalculateField" Date="20140616" Time="152325">CalculateField RideScore OBFTEXT "within 1/4 mile" VB #</Process><Process ToolSource="c:\program files (x86)\arcgis\desktop10.1\ArcToolbox\Toolboxes\Data Management Tools.tbx\CalculateField" Date="20140616" Time="152356">CalculateField RideScore OBFTEXT "&gt; 1/4 mile" VB #</Process><Process ToolSource="c:\program files (x86)\arcgis\desktop10.1\ArcToolbox\Toolboxes\Data Management Tools.tbx\CalculateField" Date="20140616" Time="153602">CalculateField RideScore WLKTEXT "1 mile &gt;=2 miles" VB #</Process><Process ToolSource="c:\program files (x86)\arcgis\desktop10.1\ArcToolbox\Toolboxes\Data Management Tools.tbx\CalculateField" Date="20140616" Time="153629">CalculateField RideScore OBDTEXT "1 mile &gt;=2 miles" VB #</Process><Process ToolSource="c:\program files (x86)\arcgis\desktop10.1\ArcToolbox\Toolboxes\Data Management Tools.tbx\CalculateField" Date="20140616" Time="153650">CalculateField RideScore OBDTEXT "1/2 mile &gt;=1 mile" VB #</Process><Process ToolSource="c:\program files (x86)\arcgis\desktop10.1\ArcToolbox\Toolboxes\Data Management Tools.tbx\CalculateField" Date="20140616" Time="153710">CalculateField RideScore OBDTEXT "1/4 mile &gt;= 1/2 mile" VB #</Process><Process ToolSource="c:\program files (x86)\arcgis\desktop10.1\ArcToolbox\Toolboxes\Data Management Tools.tbx\CalculateField" Date="20140909" Time="145209">CalculateField RideScore_062514_master RS_FINALx ((([OBFSCORE]*1.42)+([CTNSCORE]*1.42)+ ([NPPSCORE]*1.42) +([CONSCORE]*1.42)+([CCSCORE]*.72)+ ([EMPSCORE]*.72)+ ([WLKSCORE]*.72) + ([TVVSCORE]*.72) + ([DENSCORE]*.72) + ([OBDSCORE]*.72))/50)*10 VB #</Process><Process ToolSource="c:\program files (x86)\arcgis\desktop10.1\ArcToolbox\Toolboxes\Data Management Tools.tbx\CalculateField" Date="20140909" Time="145351">CalculateField RideScore_062514_master RS_FINAL [RS_FINALx] VB #</Process><Process ToolSource="c:\program files (x86)\arcgis\desktop10.1\ArcToolbox\Toolboxes\Data Management Tools.tbx\CalculateField" Date="20140909" Time="145358">CalculateField RideScore_062514_master RS_FINAL [RS_FINALx] VB #</Process><Process ToolSource="c:\program files (x86)\arcgis\desktop10.1\ArcToolbox\Toolboxes\Data Management Tools.tbx\CalculateField" Date="20140909" Time="145417">CalculateField RideScore_062514_master RS_FINAL [RS_FINALx] VB #</Process><Process ToolSource="c:\program files (x86)\arcgis\desktop10.1\ArcToolbox\Toolboxes\Data Management Tools.tbx\CalculateField" Date="20140909" Time="145439">CalculateField RideScore_062514_master SYMBOL "2" VB #</Process><Process ToolSource="c:\program files (x86)\arcgis\desktop10.1\ArcToolbox\Toolboxes\Data Management Tools.tbx\CalculateField" Date="20140909" Time="145451">CalculateField RideScore_062514_master SYMBOL "3" VB #</Process><Process ToolSource="c:\program files (x86)\arcgis\desktop10.1\ArcToolbox\Toolboxes\Data Management Tools.tbx\CalculateField" Date="20140909" Time="145504">CalculateField RideScore_062514_master SYMBOL "4" VB #</Process><Process ToolSource="c:\program files (x86)\arcgis\desktop10.1\ArcToolbox\Toolboxes\Data Management Tools.tbx\CalculateField" Date="20140909" Time="145520">CalculateField RideScore_062514_master SYMBOL "5" VB #</Process><Process ToolSource="c:\program files (x86)\arcgis\desktop10.1\ArcToolbox\Toolboxes\Data Management Tools.tbx\CalculateField" Date="20140909" Time="145532">CalculateField RideScore_062514_master SYMBOL "6" VB #</Process><Process ToolSource="c:\program files (x86)\arcgis\desktop10.1\ArcToolbox\Toolboxes\Data Management Tools.tbx\CalculateField" Date="20140909" Time="145543">CalculateField RideScore_062514_master SYMBOL "7" VB #</Process><Process ToolSource="c:\program files (x86)\arcgis\desktop10.1\ArcToolbox\Toolboxes\Data Management Tools.tbx\CalculateField" Date="20140909" Time="145555">CalculateField RideScore_062514_master SYMBOL "8" VB #</Process><Process ToolSource="c:\program files (x86)\arcgis\desktop10.1\ArcToolbox\Toolboxes\Data Management Tools.tbx\CalculateField" Date="20140909" Time="150257">CalculateField RideScore_062514_master OPERATE "SEPTA Rapid Transitl" VB #</Process><Process ToolSource="c:\program files (x86)\arcgis\desktop10.1\ArcToolbox\Toolboxes\Data Management Tools.tbx\CalculateField" Date="20140909" Time="150305">CalculateField RideScore_062514_master OPERATE "SEPTA Rapid Transit" VB #</Process><Process ToolSource="c:\program files (x86)\arcgis\desktop10.1\ArcToolbox\Toolboxes\Conversion Tools.tbx\FeatureClassToFeatureClass" Date="20140909" Time="150615">FeatureClassToFeatureClass U:\FY2013\Transportation\Trails_to_Transit\Shapefiles\RideScore_062514_master.shp U:\FY2013\Transportation\Trails_to_Transit\Shapefiles\RIDESCORE.gdb RideScore_090914 # "STATION "STATION" true true false 50 Text 0 0 ,First,#,U:\FY2013\Transportation\Trails_to_Transit\Shapefiles\RideScore_062514_master.shp,STATION,-1,-1;ZONE "ZONE" true true false 254 Text 0 0 ,First,#,U:\FY2013\Transportation\Trails_to_Transit\Shapefiles\RideScore_062514_master.shp,ZONE,-1,-1;LINE "LINE" true true false 254 Text 0 0 ,First,#,U:\FY2013\Transportation\Trails_to_Transit\Shapefiles\RideScore_062514_master.shp,LINE,-1,-1;WLKTEXT "WLKTEXT" true true false 254 Text 0 0 ,First,#,U:\FY2013\Transportation\Trails_to_Transit\Shapefiles\RideScore_062514_master.shp,WLKTEXT,-1,-1;WLKSCORE "WLKSCORE" true true false 19 Double 0 0 ,First,#,U:\FY2013\Transportation\Trails_to_Transit\Shapefiles\RideScore_062514_master.shp,WLKSCORE,-1,-1;WLKLABEL "WLKLABEL" true true false 254 Text 0 0 ,First,#,U:\FY2013\Transportation\Trails_to_Transit\Shapefiles\RideScore_062514_master.shp,WLKLABEL,-1,-1;TVVTOTAL "TVVTOTAL" true true false 19 Double 0 0 ,First,#,U:\FY2013\Transportation\Trails_to_Transit\Shapefiles\RideScore_062514_master.shp,TVVTOTAL,-1,-1;TVVSCORE "TVVSCORE" true true false 19 Double 0 0 ,First,#,U:\FY2013\Transportation\Trails_to_Transit\Shapefiles\RideScore_062514_master.shp,TVVSCORE,-1,-1;TVVLABEL "TVVLABEL" true true false 254 Text 0 0 ,First,#,U:\FY2013\Transportation\Trails_to_Transit\Shapefiles\RideScore_062514_master.shp,TVVLABEL,-1,-1;OBFTEXT "OBFTEXT" true true false 254 Text 0 0 ,First,#,U:\FY2013\Transportation\Trails_to_Transit\Shapefiles\RideScore_062514_master.shp,OBFTEXT,-1,-1;OBFSCORE "OBFSCORE" true true false 19 Double 0 0 ,First,#,U:\FY2013\Transportation\Trails_to_Transit\Shapefiles\RideScore_062514_master.shp,OBFSCORE,-1,-1;OBFLABEL "OBFLABEL" true true false 254 Text 0 0 ,First,#,U:\FY2013\Transportation\Trails_to_Transit\Shapefiles\RideScore_062514_master.shp,OBFLABEL,-1,-1;CONTOTAL "CONTOTAL" true true false 19 Double 0 0 ,First,#,U:\FY2013\Transportation\Trails_to_Transit\Shapefiles\RideScore_062514_master.shp,CONTOTAL,-1,-1;CONDENSITY "CONDENSITY" true true false 19 Double 0 0 ,First,#,U:\FY2013\Transportation\Trails_to_Transit\Shapefiles\RideScore_062514_master.shp,CONDENSITY,-1,-1;CONSCORE "CONSCORE" true true false 19 Double 0 0 ,First,#,U:\FY2013\Transportation\Trails_to_Transit\Shapefiles\RideScore_062514_master.shp,CONSCORE,-1,-1;CONLABEL "CONLABEL" true true false 254 Text 0 0 ,First,#,U:\FY2013\Transportation\Trails_to_Transit\Shapefiles\RideScore_062514_master.shp,CONLABEL,-1,-1;CTNTEXT "CTNTEXT" true true false 254 Text 0 0 ,First,#,U:\FY2013\Transportation\Trails_to_Transit\Shapefiles\RideScore_062514_master.shp,CTNTEXT,-1,-1;CTNSCORE "CTNSCORE" true true false 19 Double 0 0 ,First,#,U:\FY2013\Transportation\Trails_to_Transit\Shapefiles\RideScore_062514_master.shp,CTNSCORE,-1,-1;CTNLABEL "CTNLABEL" true true false 254 Text 0 0 ,First,#,U:\FY2013\Transportation\Trails_to_Transit\Shapefiles\RideScore_062514_master.shp,CTNLABEL,-1,-1;CCTOTAL "CCTOTAL" true true false 19 Double 0 0 ,First,#,U:\FY2013\Transportation\Trails_to_Transit\Shapefiles\RideScore_062514_master.shp,CCTOTAL,-1,-1;CCSCORE "CCSCORE" true true false 19 Double 0 0 ,First,#,U:\FY2013\Transportation\Trails_to_Transit\Shapefiles\RideScore_062514_master.shp,CCSCORE,-1,-1;CCLABEL "CCLABEL" true true false 254 Text 0 0 ,First,#,U:\FY2013\Transportation\Trails_to_Transit\Shapefiles\RideScore_062514_master.shp,CCLABEL,-1,-1;OBDTEXT "OBDTEXT" true true false 254 Text 0 0 ,First,#,U:\FY2013\Transportation\Trails_to_Transit\Shapefiles\RideScore_062514_master.shp,OBDTEXT,-1,-1;OBDSCORE "OBDSCORE" true true false 19 Double 0 0 ,First,#,U:\FY2013\Transportation\Trails_to_Transit\Shapefiles\RideScore_062514_master.shp,OBDSCORE,-1,-1;OBDLABEL "OBDLABEL" true true false 254 Text 0 0 ,First,#,U:\FY2013\Transportation\Trails_to_Transit\Shapefiles\RideScore_062514_master.shp,OBDLABEL,-1,-1;NPPTOTAL "NPPTOTAL" true true false 19 Double 0 0 ,First,#,U:\FY2013\Transportation\Trails_to_Transit\Shapefiles\RideScore_062514_master.shp,NPPTOTAL,-1,-1;NPPSCORE "NPPSCORE" true true false 19 Double 0 0 ,First,#,U:\FY2013\Transportation\Trails_to_Transit\Shapefiles\RideScore_062514_master.shp,NPPSCORE,-1,-1;NPPLABEL "NPPLABEL" true true false 254 Text 0 0 ,First,#,U:\FY2013\Transportation\Trails_to_Transit\Shapefiles\RideScore_062514_master.shp,NPPLABEL,-1,-1;EMPTOTAL "EMPTOTAL" true true false 19 Double 0 0 ,First,#,U:\FY2013\Transportation\Trails_to_Transit\Shapefiles\RideScore_062514_master.shp,EMPTOTAL,-1,-1;EMPSCORE "EMPSCORE" true true false 19 Double 0 0 ,First,#,U:\FY2013\Transportation\Trails_to_Transit\Shapefiles\RideScore_062514_master.shp,EMPSCORE,-1,-1;EMPLABEL "EMPLABEL" true true false 254 Text 0 0 ,First,#,U:\FY2013\Transportation\Trails_to_Transit\Shapefiles\RideScore_062514_master.shp,EMPLABEL,-1,-1;DENPOP "DENPOP" true true false 19 Double 0 0 ,First,#,U:\FY2013\Transportation\Trails_to_Transit\Shapefiles\RideScore_062514_master.shp,DENPOP,-1,-1;DENAREA "DENAREA" true true false 19 Double 0 0 ,First,#,U:\FY2013\Transportation\Trails_to_Transit\Shapefiles\RideScore_062514_master.shp,DENAREA,-1,-1;DENTOTAL "DENTOTAL" true true false 19 Double 0 0 ,First,#,U:\FY2013\Transportation\Trails_to_Transit\Shapefiles\RideScore_062514_master.shp,DENTOTAL,-1,-1;DENSCORE "DENSCORE" true true false 19 Double 0 0 ,First,#,U:\FY2013\Transportation\Trails_to_Transit\Shapefiles\RideScore_062514_master.shp,DENSCORE,-1,-1;DENLABEL "DENLABEL" true true false 254 Text 0 0 ,First,#,U:\FY2013\Transportation\Trails_to_Transit\Shapefiles\RideScore_062514_master.shp,DENLABEL,-1,-1;RS_FINAL "RS_FINAL" true true false 19 Double 0 0 ,First,#,U:\FY2013\Transportation\Trails_to_Transit\Shapefiles\RideScore_062514_master.shp,RS_FINAL,-1,-1;SYMBOL "SYMBOL" true true false 4 Short 0 4 ,First,#,U:\FY2013\Transportation\Trails_to_Transit\Shapefiles\RideScore_062514_master.shp,SYMBOL,-1,-1;RS_LOOKUP "RS_LOOKUP" true true false 150 Text 0 0 ,First,#,U:\FY2013\Transportation\Trails_to_Transit\Shapefiles\RideScore_062514_master.shp,RS_LOOKUP,-1,-1;OPERATE "OPERATE" true true false 50 Text 0 0 ,First,#,U:\FY2013\Transportation\Trails_to_Transit\Shapefiles\RideScore_062514_master.shp,OPERATE,-1,-1;OP "OP" true true false 50 Text 0 0 ,First,#,U:\FY2013\Transportation\Trails_to_Transit\Shapefiles\RideScore_062514_master.shp,OP,-1,-1;MCD "MCD" true true false 115 Text 0 0 ,First,#,U:\FY2013\Transportation\Trails_to_Transit\Shapefiles\RideScore_062514_master.shp,MCD,-1,-1;COUNTY "COUNTY" true true false 50 Text 0 0 ,First,#,U:\FY2013\Transportation\Trails_to_Transit\Shapefiles\RideScore_062514_master.shp,COUNTY,-1,-1;GEOID_10 "GEOID_10" true true false 10 Text 0 0 ,First,#,U:\FY2013\Transportation\Trails_to_Transit\Shapefiles\RideScore_062514_master.shp,GEOID_10,-1,-1;LOC "LOC" true true false 150 Text 0 0 ,First,#,U:\FY2013\Transportation\Trails_to_Transit\Shapefiles\RideScore_062514_master.shp,LOC,-1,-1" #</Process><Process ToolSource="c:\program files (x86)\arcgis\desktop10.1\ArcToolbox\Toolboxes\Conversion Tools.tbx\FeatureClassToFeatureClass" Date="20140909" Time="151016">FeatureClassToFeatureClass U:\FY2013\Transportation\Trails_to_Transit\Shapefiles\RIDESCORE.gdb\RideScore D:\webmaps\ridescore\data rs.shp # "STATION "STATION" true true false 50 Text 0 0 ,First,#,U:\FY2013\Transportation\Trails_to_Transit\Shapefiles\RIDESCORE.gdb\RideScore,STATION,-1,-1;ZONE "ZONE" true true false 254 Text 0 0 ,First,#,U:\FY2013\Transportation\Trails_to_Transit\Shapefiles\RIDESCORE.gdb\RideScore,ZONE,-1,-1;LINE "LINE" true true false 254 Text 0 0 ,First,#,U:\FY2013\Transportation\Trails_to_Transit\Shapefiles\RIDESCORE.gdb\RideScore,LINE,-1,-1;WLKTEXT "WLKTEXT" true true false 254 Text 0 0 ,First,#,U:\FY2013\Transportation\Trails_to_Transit\Shapefiles\RIDESCORE.gdb\RideScore,WLKTEXT,-1,-1;WLKSCORE "WLKSCORE" true true false 8 Double 0 0 ,First,#,U:\FY2013\Transportation\Trails_to_Transit\Shapefiles\RIDESCORE.gdb\RideScore,WLKSCORE,-1,-1;WLKLABEL "WLKLABEL" true true false 254 Text 0 0 ,First,#,U:\FY2013\Transportation\Trails_to_Transit\Shapefiles\RIDESCORE.gdb\RideScore,WLKLABEL,-1,-1;TVVTOTAL "TVVTOTAL" true true false 8 Double 0 0 ,First,#,U:\FY2013\Transportation\Trails_to_Transit\Shapefiles\RIDESCORE.gdb\RideScore,TVVTOTAL,-1,-1;TVVSCORE "TVVSCORE" true true false 8 Double 0 0 ,First,#,U:\FY2013\Transportation\Trails_to_Transit\Shapefiles\RIDESCORE.gdb\RideScore,TVVSCORE,-1,-1;TVVLABEL "TVVLABEL" true true false 254 Text 0 0 ,First,#,U:\FY2013\Transportation\Trails_to_Transit\Shapefiles\RIDESCORE.gdb\RideScore,TVVLABEL,-1,-1;OBFTEXT "OBFTEXT" true true false 254 Text 0 0 ,First,#,U:\FY2013\Transportation\Trails_to_Transit\Shapefiles\RIDESCORE.gdb\RideScore,OBFTEXT,-1,-1;OBFSCORE "OBFSCORE" true true false 8 Double 0 0 ,First,#,U:\FY2013\Transportation\Trails_to_Transit\Shapefiles\RIDESCORE.gdb\RideScore,OBFSCORE,-1,-1;OBFLABEL "OBFLABEL" true true false 254 Text 0 0 ,First,#,U:\FY2013\Transportation\Trails_to_Transit\Shapefiles\RIDESCORE.gdb\RideScore,OBFLABEL,-1,-1;CONTOTAL "CONTOTAL" true true false 8 Double 0 0 ,First,#,U:\FY2013\Transportation\Trails_to_Transit\Shapefiles\RIDESCORE.gdb\RideScore,CONTOTAL,-1,-1;CONDENSITY "CONDENSITY" true true false 8 Double 0 0 ,First,#,U:\FY2013\Transportation\Trails_to_Transit\Shapefiles\RIDESCORE.gdb\RideScore,CONDENSITY,-1,-1;CONSCORE "CONSCORE" true true false 8 Double 0 0 ,First,#,U:\FY2013\Transportation\Trails_to_Transit\Shapefiles\RIDESCORE.gdb\RideScore,CONSCORE,-1,-1;CONLABEL "CONLABEL" true true false 254 Text 0 0 ,First,#,U:\FY2013\Transportation\Trails_to_Transit\Shapefiles\RIDESCORE.gdb\RideScore,CONLABEL,-1,-1;CTNTEXT "CTNTEXT" true true false 254 Text 0 0 ,First,#,U:\FY2013\Transportation\Trails_to_Transit\Shapefiles\RIDESCORE.gdb\RideScore,CTNTEXT,-1,-1;CTNSCORE "CTNSCORE" true true false 8 Double 0 0 ,First,#,U:\FY2013\Transportation\Trails_to_Transit\Shapefiles\RIDESCORE.gdb\RideScore,CTNSCORE,-1,-1;CTNLABEL "CTNLABEL" true true false 254 Text 0 0 ,First,#,U:\FY2013\Transportation\Trails_to_Transit\Shapefiles\RIDESCORE.gdb\RideScore,CTNLABEL,-1,-1;CCTOTAL "CCTOTAL" true true false 8 Double 0 0 ,First,#,U:\FY2013\Transportation\Trails_to_Transit\Shapefiles\RIDESCORE.gdb\RideScore,CCTOTAL,-1,-1;CCSCORE "CCSCORE" true true false 8 Double 0 0 ,First,#,U:\FY2013\Transportation\Trails_to_Transit\Shapefiles\RIDESCORE.gdb\RideScore,CCSCORE,-1,-1;CCLABEL "CCLABEL" true true false 254 Text 0 0 ,First,#,U:\FY2013\Transportation\Trails_to_Transit\Shapefiles\RIDESCORE.gdb\RideScore,CCLABEL,-1,-1;OBDTEXT "OBDTEXT" true true false 254 Text 0 0 ,First,#,U:\FY2013\Transportation\Trails_to_Transit\Shapefiles\RIDESCORE.gdb\RideScore,OBDTEXT,-1,-1;OBDSCORE "OBDSCORE" true true false 8 Double 0 0 ,First,#,U:\FY2013\Transportation\Trails_to_Transit\Shapefiles\RIDESCORE.gdb\RideScore,OBDSCORE,-1,-1;OBDLABEL "OBDLABEL" true true false 254 Text 0 0 ,First,#,U:\FY2013\Transportation\Trails_to_Transit\Shapefiles\RIDESCORE.gdb\RideScore,OBDLABEL,-1,-1;NPPTOTAL "NPPTOTAL" true true false 8 Double 0 0 ,First,#,U:\FY2013\Transportation\Trails_to_Transit\Shapefiles\RIDESCORE.gdb\RideScore,NPPTOTAL,-1,-1;NPPSCORE "NPPSCORE" true true false 8 Double 0 0 ,First,#,U:\FY2013\Transportation\Trails_to_Transit\Shapefiles\RIDESCORE.gdb\RideScore,NPPSCORE,-1,-1;NPPLABEL "NPPLABEL" true true false 254 Text 0 0 ,First,#,U:\FY2013\Transportation\Trails_to_Transit\Shapefiles\RIDESCORE.gdb\RideScore,NPPLABEL,-1,-1;EMPTOTAL "EMPTOTAL" true true false 8 Double 0 0 ,First,#,U:\FY2013\Transportation\Trails_to_Transit\Shapefiles\RIDESCORE.gdb\RideScore,EMPTOTAL,-1,-1;EMPSCORE "EMPSCORE" true true false 8 Double 0 0 ,First,#,U:\FY2013\Transportation\Trails_to_Transit\Shapefiles\RIDESCORE.gdb\RideScore,EMPSCORE,-1,-1;EMPLABEL "EMPLABEL" true true false 254 Text 0 0 ,First,#,U:\FY2013\Transportation\Trails_to_Transit\Shapefiles\RIDESCORE.gdb\RideScore,EMPLABEL,-1,-1;DENPOP "DENPOP" true true false 8 Double 0 0 ,First,#,U:\FY2013\Transportation\Trails_to_Transit\Shapefiles\RIDESCORE.gdb\RideScore,DENPOP,-1,-1;DENAREA "DENAREA" true true false 8 Double 0 0 ,First,#,U:\FY2013\Transportation\Trails_to_Transit\Shapefiles\RIDESCORE.gdb\RideScore,DENAREA,-1,-1;DENTOTAL "DENTOTAL" true true false 8 Double 0 0 ,First,#,U:\FY2013\Transportation\Trails_to_Transit\Shapefiles\RIDESCORE.gdb\RideScore,DENTOTAL,-1,-1;DENSCORE "DENSCORE" true true false 8 Double 0 0 ,First,#,U:\FY2013\Transportation\Trails_to_Transit\Shapefiles\RIDESCORE.gdb\RideScore,DENSCORE,-1,-1;DENLABEL "DENLABEL" true true false 254 Text 0 0 ,First,#,U:\FY2013\Transportation\Trails_to_Transit\Shapefiles\RIDESCORE.gdb\RideScore,DENLABEL,-1,-1;RS_FINAL "RS_FINAL" true true false 8 Double 0 0 ,First,#,U:\FY2013\Transportation\Trails_to_Transit\Shapefiles\RIDESCORE.gdb\RideScore,RS_FINAL,-1,-1;SYMBOL "SYMBOL" true true false 2 Short 0 0 ,First,#,U:\FY2013\Transportation\Trails_to_Transit\Shapefiles\RIDESCORE.gdb\RideScore,SYMBOL,-1,-1;RS_LOOKUP "RS_LOOKUP" true true false 150 Text 0 0 ,First,#,U:\FY2013\Transportation\Trails_to_Transit\Shapefiles\RIDESCORE.gdb\RideScore,RS_LOOKUP,-1,-1;OPERATE "OPERATE" true true false 50 Text 0 0 ,First,#,U:\FY2013\Transportation\Trails_to_Transit\Shapefiles\RIDESCORE.gdb\RideScore,OPERATE,-1,-1;OP "OP" true true false 50 Text 0 0 ,First,#,U:\FY2013\Transportation\Trails_to_Transit\Shapefiles\RIDESCORE.gdb\RideScore,OP,-1,-1;MCD "MCD" true true false 115 Text 0 0 ,First,#,U:\FY2013\Transportation\Trails_to_Transit\Shapefiles\RIDESCORE.gdb\RideScore,MCD,-1,-1;COUNTY "COUNTY" true true false 50 Text 0 0 ,First,#,U:\FY2013\Transportation\Trails_to_Transit\Shapefiles\RIDESCORE.gdb\RideScore,COUNTY,-1,-1;GEOID_10 "GEOID_10" true true false 10 Text 0 0 ,First,#,U:\FY2013\Transportation\Trails_to_Transit\Shapefiles\RIDESCORE.gdb\RideScore,GEOID_10,-1,-1;LOC "LOC" true true false 150 Text 0 0 ,First,#,U:\FY2013\Transportation\Trails_to_Transit\Shapefiles\RIDESCORE.gdb\RideScore,LOC,-1,-1" #</Process></lineage><itemProps><itemName Sync="TRUE">DVRPC_RideScore</itemName><imsContentType Sync="TRUE">002</imsContentType><itemLocation><linkage Sync="TRUE">file://\\dvrpc_filesrv\user_projects\_OngoingProjects\Traffic Counts\Hackathon\RideScore\DVRPC_RideScore.shp</linkage><protocol Sync="TRUE">Local Area Network</protocol></itemLocation><itemSize Sync="TRUE">0.012</itemSize><nativeExtBox><westBL Sync="TRUE">-75.762948</westBL><eastBL Sync="TRUE">-74.624213</eastBL><southBL Sync="TRUE">39.783609</southBL><northBL Sync="TRUE">40.343017</northBL><exTypeCode Sync="TRUE">1</exTypeCode></nativeExtBox></itemProps><coordRef><type Sync="TRUE">Geographic</type><geogcsn Sync="TRUE">GCS_WGS_1984</geogcsn><csUnits Sync="TRUE">Angular Unit: Degree (0.017453)</csUnits><peXml Sync="TRUE">&lt;GeographicCoordinateSystem xsi:type='typens:GeographicCoordinateSystem' xmlns:xsi='http://www.w3.org/2001/XMLSchema-instance' xmlns:xs='http://www.w3.org/2001/XMLSchema' xmlns:typens='http://www.esri.com/schemas/ArcGIS/10.3'&gt;&lt;WKT&gt;GEOGCS[&amp;quot;GCS_WGS_1984&amp;quot;,DATUM[&amp;quot;D_WGS_1984&amp;quot;,SPHEROID[&amp;quot;WGS_1984&amp;quot;,6378137.0,298.257223563]],PRIMEM[&amp;quot;Greenwich&amp;quot;,0.0],UNIT[&amp;quot;Degree&amp;quot;,0.0174532925199433],AUTHORITY[&amp;quot;EPSG&amp;quot;,4326]]&lt;/WKT&gt;&lt;XOrigin&gt;-400&lt;/XOrigin&gt;&lt;YOrigin&gt;-400&lt;/YOrigin&gt;&lt;XYScale&gt;11258999068426.238&lt;/XYScale&gt;&lt;ZOrigin&gt;-100000&lt;/ZOrigin&gt;&lt;ZScale&gt;10000&lt;/ZScale&gt;&lt;MOrigin&gt;-100000&lt;/MOrigin&gt;&lt;MScale&gt;10000&lt;/MScale&gt;&lt;XYTolerance&gt;8.983152841195215e-009&lt;/XYTolerance&gt;&lt;ZTolerance&gt;0.001&lt;/ZTolerance&gt;&lt;MTolerance&gt;0.001&lt;/MTolerance&gt;&lt;HighPrecision&gt;true&lt;/HighPrecision&gt;&lt;LeftLongitude&gt;-180&lt;/LeftLongitude&gt;&lt;WKID&gt;4326&lt;/WKID&gt;&lt;LatestWKID&gt;4326&lt;/LatestWKID&gt;&lt;/GeographicCoordinateSystem&gt;</peXml></coordRef><copyHistory><copy source="D:\webmaps\ridescore\data\rs" dest="\\CPOLLARD\D$\webmaps\ridescore\data\_GIS\rs" date="20140909" time="15102800"></copy></copyHistory></DataProperties><SyncDate>20150604</SyncDate><SyncTime>14290700</SyncTime><ModDate>20150604</ModDate><ModTime>14290700</ModTime></Esri><dataIdInfo><envirDesc Sync="TRUE">Microsoft Windows 7 Version 6.1 (Build 7601) Service Pack 1; Esri ArcGIS 10.3.0.4322</envirDesc><dataLang><languageCode value="eng" Sync="TRUE"></languageCode><countryCode value="USA" Sync="TRUE"></countryCode></dataLang><idCitation><resTitle Sync="TRUE">DVRPC_RideScore</resTitle><presForm><PresFormCd value="005" Sync="TRUE"></PresFormCd></presForm></idCitation><spatRpType><SpatRepTypCd value="001" Sync="TRUE"></SpatRepTypCd></spatRpType><dataExt><geoEle><GeoBndBox esriExtentType="search"><exTypeCode Sync="TRUE">1</exTypeCode><westBL Sync="TRUE">-75.762948</westBL><eastBL Sync="TRUE">-74.624213</eastBL><northBL Sync="TRUE">40.343017</northBL><southBL Sync="TRUE">39.783609</southBL></GeoBndBox></geoEle></dataExt></dataIdInfo><mdLang><languageCode value="eng" Sync="TRUE"></languageCode><countryCode value="USA" Sync="TRUE"></countryCode></mdLang><distInfo><distFormat><formatName Sync="TRUE">Shapefile</formatName></distFormat><distTranOps><transSize Sync="TRUE">0.012</transSize></distTranOps></distInfo><mdHrLv><ScopeCd value="005" Sync="TRUE"></ScopeCd></mdHrLv><mdHrLvName Sync="TRUE">dataset</mdHrLvName><refSysInfo><RefSystem><refSysID><identCode code="4326" Sync="TRUE"></identCode><idCodeSpace Sync="TRUE">EPSG</idCodeSpace><idVersion Sync="TRUE">8.2.6</idVersion></refSysID></RefSystem></refSysInfo><spatRepInfo><VectSpatRep><geometObjs Name="DVRPC_RideScore"><geoObjTyp><GeoObjTypCd value="001" Sync="TRUE"></GeoObjTypCd></geoObjTyp><geoObjCnt Sync="TRUE">195</geoObjCnt></geometObjs><topLvl><TopoLevCd value="001" Sync="TRUE"></TopoLevCd></topLvl></VectSpatRep></spatRepInfo><spdoinfo><ptvctinf><esriterm Name="DVRPC_RideScore"><efeatyp Sync="TRUE">Simple</efeatyp><efeageom code="2" Sync="TRUE"></efeageom><esritopo Sync="TRUE">FALSE</esritopo><efeacnt Sync="TRUE">195</efeacnt><spindex Sync="TRUE">TRUE</spindex><linrefer Sync="TRUE">FALSE</linrefer></esriterm></ptvctinf></spdoinfo><eainfo><detailed Name="DVRPC_RideScore"><enttyp><enttypl Sync="TRUE">DVRPC_RideScore</enttypl><enttypt Sync="TRUE">Feature Class</enttypt><enttypc Sync="TRUE">195</enttypc></enttyp><attr><attrlabl Sync="TRUE">FID</attrlabl><attalias Sync="TRUE">FID</attalias><attrtype Sync="TRUE">OID</attrtype><attwidth Sync="TRUE">4</attwidth><atprecis Sync="TRUE">0</atprecis><attscale Sync="TRUE">0</attscale><attrdef Sync="TRUE">Internal feature number.</attrdef><attrdefs Sync="TRUE">Esri</attrdefs><attrdomv><udom Sync="TRUE">Sequential unique whole numbers that are automatically generated.</udom></attrdomv></attr><attr><attrlabl Sync="TRUE">Shape</attrlabl><attalias Sync="TRUE">Shape</attalias><attrtype Sync="TRUE">Geometry</attrtype><attwidth Sync="TRUE">0</attwidth><atprecis Sync="TRUE">0</atprecis><attscale Sync="TRUE">0</attscale><attrdef Sync="TRUE">Feature geometry.</attrdef><attrdefs Sync="TRUE">Esri</attrdefs><attrdomv><udom Sync="TRUE">Coordinates defining the features.</udom></attrdomv></attr><attr><attrlabl Sync="TRUE">STATION</attrlabl><attalias Sync="TRUE">STATION</attalias><attrtype Sync="TRUE">String</attrtype><attwidth Sync="TRUE">50</attwidth><atprecis Sync="TRUE">0</atprecis><attscale Sync="TRUE">0</attscale></attr><attr><attrlabl Sync="TRUE">ZONE</attrlabl><attalias Sync="TRUE">ZONE</attalias><attrtype Sync="TRUE">String</attrtype><attwidth Sync="TRUE">254</attwidth><atprecis Sync="TRUE">0</atprecis><attscale Sync="TRUE">0</attscale></attr><attr><attrlabl Sync="TRUE">LINE</attrlabl><attalias Sync="TRUE">LINE</attalias><attrtype Sync="TRUE">String</attrtype><attwidth Sync="TRUE">254</attwidth><atprecis Sync="TRUE">0</atprecis><attscale Sync="TRUE">0</attscale></attr><attr><attrlabl Sync="TRUE">WLKTEXT</attrlabl><attalias Sync="TRUE">WLKTEXT</attalias><attrtype Sync="TRUE">String</attrtype><attwidth Sync="TRUE">254</attwidth><atprecis Sync="TRUE">0</atprecis><attscale Sync="TRUE">0</attscale></attr><attr><attrlabl Sync="TRUE">WLKSCORE</attrlabl><attalias Sync="TRUE">WLKSCORE</attalias><attrtype Sync="TRUE">Double</attrtype><attwidth Sync="TRUE">19</attwidth><atprecis Sync="TRUE">0</atprecis><attscale Sync="TRUE">0</attscale></attr><attr><attrlabl Sync="TRUE">WLKLABEL</attrlabl><attalias Sync="TRUE">WLKLABEL</attalias><attrtype Sync="TRUE">String</attrtype><attwidth Sync="TRUE">254</attwidth><atprecis Sync="TRUE">0</atprecis><attscale Sync="TRUE">0</attscale></attr><attr><attrlabl Sync="TRUE">TVVTOTAL</attrlabl><attalias Sync="TRUE">TVVTOTAL</attalias><attrtype Sync="TRUE">Double</attrtype><attwidth Sync="TRUE">19</attwidth><atprecis Sync="TRUE">0</atprecis><attscale Sync="TRUE">0</attscale></attr><attr><attrlabl Sync="TRUE">TVVSCORE</attrlabl><attalias Sync="TRUE">TVVSCORE</attalias><attrtype Sync="TRUE">Double</attrtype><attwidth Sync="TRUE">19</attwidth><atprecis Sync="TRUE">0</atprecis><attscale Sync="TRUE">0</attscale></attr><attr><attrlabl Sync="TRUE">TVVLABEL</attrlabl><attalias Sync="TRUE">TVVLABEL</attalias><attrtype Sync="TRUE">String</attrtype><attwidth Sync="TRUE">254</attwidth><atprecis Sync="TRUE">0</atprecis><attscale Sync="TRUE">0</attscale></attr><attr><attrlabl Sync="TRUE">OBFTEXT</attrlabl><attalias Sync="TRUE">OBFTEXT</attalias><attrtype Sync="TRUE">String</attrtype><attwidth Sync="TRUE">254</attwidth><atprecis Sync="TRUE">0</atprecis><attscale Sync="TRUE">0</attscale></attr><attr><attrlabl Sync="TRUE">OBFSCORE</attrlabl><attalias Sync="TRUE">OBFSCORE</attalias><attrtype Sync="TRUE">Double</attrtype><attwidth Sync="TRUE">19</attwidth><atprecis Sync="TRUE">0</atprecis><attscale Sync="TRUE">0</attscale></attr><attr><attrlabl Sync="TRUE">OBFLABEL</attrlabl><attalias Sync="TRUE">OBFLABEL</attalias><attrtype Sync="TRUE">String</attrtype><attwidth Sync="TRUE">254</attwidth><atprecis Sync="TRUE">0</atprecis><attscale Sync="TRUE">0</attscale></attr><attr><attrlabl Sync="TRUE">CONTOTAL</attrlabl><attalias Sync="TRUE">CONTOTAL</attalias><attrtype Sync="TRUE">Double</attrtype><attwidth Sync="TRUE">19</attwidth><atprecis Sync="TRUE">0</atprecis><attscale Sync="TRUE">0</attscale></attr><attr><attrlabl Sync="TRUE">CONDENSITY</attrlabl><attalias Sync="TRUE">CONDENSITY</attalias><attrtype Sync="TRUE">Double</attrtype><attwidth Sync="TRUE">19</attwidth><atprecis Sync="TRUE">0</atprecis><attscale Sync="TRUE">0</attscale></attr><attr><attrlabl Sync="TRUE">CONSCORE</attrlabl><attalias Sync="TRUE">CONSCORE</attalias><attrtype Sync="TRUE">Double</attrtype><attwidth Sync="TRUE">19</attwidth><atprecis Sync="TRUE">0</atprecis><attscale Sync="TRUE">0</attscale></attr><attr><attrlabl Sync="TRUE">CONLABEL</attrlabl><attalias Sync="TRUE">CONLABEL</attalias><attrtype Sync="TRUE">String</attrtype><attwidth Sync="TRUE">254</attwidth><atprecis Sync="TRUE">0</atprecis><attscale Sync="TRUE">0</attscale></attr><attr><attrlabl Sync="TRUE">CTNTEXT</attrlabl><attalias Sync="TRUE">CTNTEXT</attalias><attrtype Sync="TRUE">String</attrtype><attwidth Sync="TRUE">254</attwidth><atprecis Sync="TRUE">0</atprecis><attscale Sync="TRUE">0</attscale></attr><attr><attrlabl Sync="TRUE">CTNSCORE</attrlabl><attalias Sync="TRUE">CTNSCORE</attalias><attrtype Sync="TRUE">Double</attrtype><attwidth Sync="TRUE">19</attwidth><atprecis Sync="TRUE">0</atprecis><attscale Sync="TRUE">0</attscale></attr><attr><attrlabl Sync="TRUE">CTNLABEL</attrlabl><attalias Sync="TRUE">CTNLABEL</attalias><attrtype Sync="TRUE">String</attrtype><attwidth Sync="TRUE">254</attwidth><atprecis Sync="TRUE">0</atprecis><attscale Sync="TRUE">0</attscale></attr><attr><attrlabl Sync="TRUE">CCTOTAL</attrlabl><attalias Sync="TRUE">CCTOTAL</attalias><attrtype Sync="TRUE">Double</attrtype><attwidth Sync="TRUE">19</attwidth><atprecis Sync="TRUE">0</atprecis><attscale Sync="TRUE">0</attscale></attr><attr><attrlabl Sync="TRUE">CCSCORE</attrlabl><attalias Sync="TRUE">CCSCORE</attalias><attrtype Sync="TRUE">Double</attrtype><attwidth Sync="TRUE">19</attwidth><atprecis Sync="TRUE">0</atprecis><attscale Sync="TRUE">0</attscale></attr><attr><attrlabl Sync="TRUE">CCLABEL</attrlabl><attalias Sync="TRUE">CCLABEL</attalias><attrtype Sync="TRUE">String</attrtype><attwidth Sync="TRUE">254</attwidth><atprecis Sync="TRUE">0</atprecis><attscale Sync="TRUE">0</attscale></attr><attr><attrlabl Sync="TRUE">OBDTEXT</attrlabl><attalias Sync="TRUE">OBDTEXT</attalias><attrtype Sync="TRUE">String</attrtype><attwidth Sync="TRUE">254</attwidth><atprecis Sync="TRUE">0</atprecis><attscale Sync="TRUE">0</attscale></attr><attr><attrlabl Sync="TRUE">OBDSCORE</attrlabl><attalias Sync="TRUE">OBDSCORE</attalias><attrtype Sync="TRUE">Double</attrtype><attwidth Sync="TRUE">19</attwidth><atprecis Sync="TRUE">0</atprecis><attscale Sync="TRUE">0</attscale></attr><attr><attrlabl Sync="TRUE">OBDLABEL</attrlabl><attalias Sync="TRUE">OBDLABEL</attalias><attrtype Sync="TRUE">String</attrtype><attwidth Sync="TRUE">254</attwidth><atprecis Sync="TRUE">0</atprecis><attscale Sync="TRUE">0</attscale></attr><attr><attrlabl Sync="TRUE">NPPTOTAL</attrlabl><attalias Sync="TRUE">NPPTOTAL</attalias><attrtype Sync="TRUE">Double</attrtype><attwidth Sync="TRUE">19</attwidth><atprecis Sync="TRUE">0</atprecis><attscale Sync="TRUE">0</attscale></attr><attr><attrlabl Sync="TRUE">NPPSCORE</attrlabl><attalias Sync="TRUE">NPPSCORE</attalias><attrtype Sync="TRUE">Double</attrtype><attwidth Sync="TRUE">19</attwidth><atprecis Sync="TRUE">0</atprecis><attscale Sync="TRUE">0</attscale></attr><attr><attrlabl Sync="TRUE">NPPLABEL</attrlabl><attalias Sync="TRUE">NPPLABEL</attalias><attrtype Sync="TRUE">String</attrtype><attwidth Sync="TRUE">254</attwidth><atprecis Sync="TRUE">0</atprecis><attscale Sync="TRUE">0</attscale></attr><attr><attrlabl Sync="TRUE">EMPTOTAL</attrlabl><attalias Sync="TRUE">EMPTOTAL</attalias><attrtype Sync="TRUE">Double</attrtype><attwidth Sync="TRUE">19</attwidth><atprecis Sync="TRUE">0</atprecis><attscale Sync="TRUE">0</attscale></attr><attr><attrlabl Sync="TRUE">EMPSCORE</attrlabl><attalias Sync="TRUE">EMPSCORE</attalias><attrtype Sync="TRUE">Double</attrtype><attwidth Sync="TRUE">19</attwidth><atprecis Sync="TRUE">0</atprecis><attscale Sync="TRUE">0</attscale></attr><attr><attrlabl Sync="TRUE">EMPLABEL</attrlabl><attalias Sync="TRUE">EMPLABEL</attalias><attrtype Sync="TRUE">String</attrtype><attwidth Sync="TRUE">254</attwidth><atprecis Sync="TRUE">0</atprecis><attscale Sync="TRUE">0</attscale></attr><attr><attrlabl Sync="TRUE">DENPOP</attrlabl><attalias Sync="TRUE">DENPOP</attalias><attrtype Sync="TRUE">Double</attrtype><attwidth Sync="TRUE">19</attwidth><atprecis Sync="TRUE">0</atprecis><attscale Sync="TRUE">0</attscale></attr><attr><attrlabl Sync="TRUE">DENAREA</attrlabl><attalias Sync="TRUE">DENAREA</attalias><attrtype Sync="TRUE">Double</attrtype><attwidth Sync="TRUE">19</attwidth><atprecis Sync="TRUE">0</atprecis><attscale Sync="TRUE">0</attscale></attr><attr><attrlabl Sync="TRUE">DENTOTAL</attrlabl><attalias Sync="TRUE">DENTOTAL</attalias><attrtype Sync="TRUE">Double</attrtype><attwidth Sync="TRUE">19</attwidth><atprecis Sync="TRUE">0</atprecis><attscale Sync="TRUE">0</attscale></attr><attr><attrlabl Sync="TRUE">DENSCORE</attrlabl><attalias Sync="TRUE">DENSCORE</attalias><attrtype Sync="TRUE">Double</attrtype><attwidth Sync="TRUE">19</attwidth><atprecis Sync="TRUE">0</atprecis><attscale Sync="TRUE">0</attscale></attr><attr><attrlabl Sync="TRUE">DENLABEL</attrlabl><attalias Sync="TRUE">DENLABEL</attalias><attrtype Sync="TRUE">String</attrtype><attwidth Sync="TRUE">254</attwidth><atprecis Sync="TRUE">0</atprecis><attscale Sync="TRUE">0</attscale></attr><attr><attrlabl Sync="TRUE">RS_FINAL</attrlabl><attalias Sync="TRUE">RS_FINAL</attalias><attrtype Sync="TRUE">Double</attrtype><attwidth Sync="TRUE">19</attwidth><atprecis Sync="TRUE">0</atprecis><attscale Sync="TRUE">0</attscale></attr><attr><attrlabl Sync="TRUE">SYMBOL</attrlabl><attalias Sync="TRUE">SYMBOL</attalias><attrtype Sync="TRUE">SmallInteger</attrtype><attwidth Sync="TRUE">4</attwidth><atprecis Sync="TRUE">4</atprecis><attscale Sync="TRUE">0</attscale></attr><attr><attrlabl Sync="TRUE">RS_LOOKUP</attrlabl><attalias Sync="TRUE">RS_LOOKUP</attalias><attrtype Sync="TRUE">String</attrtype><attwidth Sync="TRUE">150</attwidth><atprecis Sync="TRUE">0</atprecis><attscale Sync="TRUE">0</attscale></attr><attr><attrlabl Sync="TRUE">OPERATE</attrlabl><attalias Sync="TRUE">OPERATE</attalias><attrtype Sync="TRUE">String</attrtype><attwidth Sync="TRUE">50</attwidth><atprecis Sync="TRUE">0</atprecis><attscale Sync="TRUE">0</attscale></attr><attr><attrlabl Sync="TRUE">OP</attrlabl><attalias Sync="TRUE">OP</attalias><attrtype Sync="TRUE">String</attrtype><attwidth Sync="TRUE">50</attwidth><atprecis Sync="TRUE">0</atprecis><attscale Sync="TRUE">0</attscale></attr><attr><attrlabl Sync="TRUE">MCD</attrlabl><attalias Sync="TRUE">MCD</attalias><attrtype Sync="TRUE">String</attrtype><attwidth Sync="TRUE">115</attwidth><atprecis Sync="TRUE">0</atprecis><attscale Sync="TRUE">0</attscale></attr><attr><attrlabl Sync="TRUE">COUNTY</attrlabl><attalias Sync="TRUE">COUNTY</attalias><attrtype Sync="TRUE">String</attrtype><attwidth Sync="TRUE">50</attwidth><atprecis Sync="TRUE">0</atprecis><attscale Sync="TRUE">0</attscale></attr><attr><attrlabl Sync="TRUE">GEOID_10</attrlabl><attalias Sync="TRUE">GEOID_10</attalias><attrtype Sync="TRUE">String</attrtype><attwidth Sync="TRUE">10</attwidth><atprecis Sync="TRUE">0</atprecis><attscale Sync="TRUE">0</attscale></attr><attr><attrlabl Sync="TRUE">LOC</attrlabl><attalias Sync="TRUE">LOC</attalias><attrtype Sync="TRUE">String</attrtype><attwidth Sync="TRUE">150</attwidth><atprecis Sync="TRUE">0</atprecis><attscale Sync="TRUE">0</attscale></attr></detailed></eainfo><mdDateSt Sync="TRUE">20150604</mdDateSt><Binary><Thumbnail><Data EsriPropertyType="PictureX">/9j/4AAQSkZJRgABAQEAAQABAAD/2wBDAAgGBgcGBQgHBwcJCQgKDBQNDAsLDBkSEw8UHRofHh0a
HBwgJC4nICIsIxwcKDcpLDAxNDQ0Hyc5PTgyPC4zNDL/2wBDAQkJCQwLDBgNDRgyIRwhMjIyMjIy
MjIyMjIyMjIyMjIyMjIyMjIyMjIyMjIyMjIyMjIyMjIyMjIyMjIyMjIyMjL/wAARCACFAMgDASIA
AhEBAxEB/8QAHwAAAQUBAQEBAQEAAAAAAAAAAAECAwQFBgcICQoL/8QAtRAAAgEDAwIEAwUFBAQA
AAF9AQIDAAQRBRIhMUEGE1FhByJxFDKBkaEII0KxwRVS0fAkM2JyggkKFhcYGRolJicoKSo0NTY3
ODk6Q0RFRkdISUpTVFVWV1hZWmNkZWZnaGlqc3R1dnd4eXqDhIWGh4iJipKTlJWWl5iZmqKjpKWm
p6ipqrKztLW2t7i5usLDxMXGx8jJytLT1NXW19jZ2uHi4+Tl5ufo6erx8vP09fb3+Pn6/8QAHwEA
AwEBAQEBAQEBAQAAAAAAAAECAwQFBgcICQoL/8QAtREAAgECBAQDBAcFBAQAAQJ3AAECAxEEBSEx
BhJBUQdhcRMiMoEIFEKRobHBCSMzUvAVYnLRChYkNOEl8RcYGRomJygpKjU2Nzg5OkNERUZHSElK
U1RVVldYWVpjZGVmZ2hpanN0dXZ3eHl6goOEhYaHiImKkpOUlZaXmJmaoqOkpaanqKmqsrO0tba3
uLm6wsPExcbHyMnK0tPU1dbX2Nna4uPk5ebn6Onq8vP09fb3+Pn6/9oADAMBAAIRAxEAPwD3+iii
gAooooAKKKKACiiigAooooAKKKKACiio5p4bdA88scSFlQM7BQWJwBz3JIA9zQBJRRRQAUUUUAFF
FFABRRRQAU1HSRdyMrAErlTnkHBH4EEU6suRbHwzo9zNaadIIEZpmt7GDc7szZYhR1JJz/8AqoA1
KKAcjNFABRRRQAUUUUAFFFFABRRRQAUUUUAFUIta0+bXJ9GjuA9/bwrPLEqk7EY4GTjAJx0znHNM
1nVRpKWbvErQz3KW8kjzpEIg2QGyxGecDA5OeKNH0Oz0S2MdsHklcDzrmdt805HALv1YgcDPQUAR
tZ6lqNnJFfXP2J1vPMhfT5DloVcMocsvVgMMBxg9akh0W3+wm0vnk1NPtDXCm+CyFW371A4Awpxt
9ABWlRQAUUUUAFFFFABRRVTUNSttNjha6d0E8yW8ZSNny7nCjgHHPc8UAW6KqabaTWOnQW1xezX0
sa4a4nCh5Pc7QB+lW6ACiqlpbXUFzeST3z3Ec0oeGNo1UQLtA2gjluQTk+uO1W6ACiiigAooooAK
KKKACiiigAooooAKKKKAKGs2M2o6XNbW00MFwdrRTTQCZY3VgQ2w4BII49Dg9qvjOOetFYZU6DfX
NyWjj0mbzbu9uru9YmGT5AAobIVMA8ZAH8wDcopFZXRXRgysMgg5BFLQBUudSs7S9s7Oe4WO4vGZ
beM5zIVXc2PoKt1UtoLxL68luLtJreRlNtCIQpgAXDAtn5snJ6DGcVboAKKKKAIzPCtwlu0sYmdS
6xlhuZRgEgdSBkfmKkrN0+TT9Y8nWIrMiZBJDHLcWxjmRd2GHzAMASv48VpUAFYPh9NbTUdeOru7
QNfZsM7Nog8tMYxyOd2c9+e9b1FABRRRQAUUUUAFFFFABRRRQAUUUUAFFFFABWYNf05vEh8PrOW1
Jbb7W8aqSEj3BQS3QEk9OtadctbabZy/Eu+1KW6ae+h06KKGA27KtvEzMSQ5+VixXtyAMUAdTUc0
EVzBJBPEksMilXjdQysD1BB6inGRFKguoLnaoJ6nBOB74B/KnUAZMd8dHt7ePXNQtfPurtoLZo4j
GrbixjTGTyFHXpx+br/XLO2RI4bmGS6nkFvAo3OvmshZA+wEqCBnJ7c0W2q6Nr0mo6dBc2141q5t
7y34bYSCCrA9jyPTqOxrH/4Re5sJ7q10lorXTtRURSSWwSCaxRIdieWQh8w5A5Y/KOlAGto8DaJ4
dhTUrsmWKJprmaa4aQKTln+dudgJIGegApsniGCRANNhmv5pbFr228pSIp142qJSNgJJHBPTmo7T
QNG0i4tZ3ZnuwZYoZ7y4LyMZW3ugLHnJXOB6HHettVVEVEUKqjAAGABQBjwf2zqum28lyp0S6W6D
yQxulxviVz8pbGBuXHTkZ61e03TodKsVtLd53jVmYGeZpXyzFjlmJJ5NW6qXupQWElqkqzMbmcW6
eVC0m1iCcttB2jjqeBQBbprqWjZVYoxBAYDOD681Wspb52u/t0EEKJMRbmKUvviwMM2QNpznjnp1
qvo7Ws8l/dWertqEU1wcjzlkS3ZVCmNdvQcZIPck96AJIXOj6Esmq6iJvskG65vZVWMNtGWcgcL0
Jq0kkN7aLJFIssE8YZXjbhlYcEEeoPUVBbW12s199tuo7m3mkzBF5IXyo9oBQnJ3ZIJyfXFXAABg
DAFAFbTrC30rTrewtFZLa3jEcas5chQMAZJJP41ZoooAKKKKACiigEHoc0AFFVNO1K11W2a4tHdo
1leEl42Q7kYqwwwB6g81Bqx1giKLSUtB5iyLJcXDE+Qdh2MEA+cbsZGRxQBpUVHAJlt4luHR5ggE
jou1WbHJAycDPbJqQgEYIyDQBQm1nT4I7KQ3AkjvphBbvCpkV3IJHKggD5TyeKo/8JRDMrvY6dqN
7EkdwxkhgwN8LbWj+Yg7ycheMHB5rWtLO10+0jtbO3it7eMYSKJAqqPYDgVPQBzl54u/s5JJr7Qt
YigUrtkjtvOyDEZCSqElcY2HI+9jtkjFtfElp4g+JdvbacI45NNgmjujds8UxDEZSOEkE8rG28qR
g4BB697XFePPBU/iEW2q6LdfYfEFic28+9kWVM8xOVIIU+o5/OgDoY/DmjwukkenW4kS6e8RmXcV
ncEM4z0Jyf8AIFWdNS+h06CPU7iCe9AxLLDGY0Y+yknHHvXGeHPHcw0xX1+JxHDbs9xqCINsckeT
KkyJu8lhwACSW9AeKteIdY8LavoEWoXV9PBFFdm3gvoY3SS1mYtDvBI+UcsNxG38cUAcb4h8PTeD
/H6ajoGq/wBnm8tby+fzzG/nuhR3hJkIIQjc2SflJJzjp32vzWut+HNPie/s7T+0Lm3CCWUsJGDh
zErRuMt8hAIPUVn67ot94mt7DTtU09be4t7hrqHUUYTxRCOQAK4JQkyRlgVxjk/hb8PaRomqeE7q
0gls7zSb2eaSMWcP2cRpISdnynIYBiM8HBoAlv8ATtW1rxbZNNDFbaNpU3nqXVJHu5SmFK5zsCln
z0OQMe3UVnatFfLosqaVMYbqNVMZ8sSlgpBKgMwBLAFckjrnNYd499rOhzXGvwjRtIRJTe2rv5kk
1uYs5LoQYyCTkLk/L19QDor2S/je0FjbwTK04W4MspTZFg5ZcA7mzjjjr1FZuj3Gl3Gu622m2hE3
mRrdXqkNHNKqldoIY/MgGCMDGffNL4c1ebWoDdxWTQaS8afYpJiyzSD5gxdGHyjhSDk5Bzx0rYhg
htw4hijjDuXYIoG5icknHUk96AKtnZTnRkstXni1CVozHcSeSESUHIOUyQBg4xUmn6bZaTZR2en2
kNrbRjCxQoFUfgKtUUAFFFFABRRRQAUUUUAFVNO02z0iyWzsLdYLdWZljXOAWYsevuTVuigAoooo
AKKKKACiiigAooooA4TxJpUnhjWR4v0O1kKyMses2kEQYTwZJM2wEEyL6jJIJz3rSh0TQNfk1y/s
b2Yy6iY7a8ltpijxPB0A4yjjPINWPEPiu30W4g061gbUNbugTbafC6h2H99ifuJnqx9+uDiS2j8Q
3F0skgsdMgjkZjDGPPM4aMfePy7SshJ4+9jt1IBugYGKxdL0T+y9f1W7t4rWO0v/AC5mCbzK0wBV
i2TtC7QmAAOc1Na2erA6ZLeaqrSQQst5FDAFjuXIGG5yVwQeh5z+FalAEF3e2thEst5cw28bOsYe
VwoLMcKMnuSQBVCDTpr6S2vNZhgF7ZzzNb/Zpn2BGyq7gcAkoRnIIznFW7mbT5bqLT7p7Z7iQedH
bylSzBCDvCn+6dpz2OKc+o2ceow6e91Et5NG0scBYb2VSASB6DIoAs0UUUAFFFFABRRRQAUUUUAF
FFFABRRRQAUUUUAFFFFABRRRQBy8/h7W472LUrXXzLfRR3Me26iPkyK5LRKUQgDYdvzAbiB+FXZ4
deuILqKa+tLBFjgaK7tl3MGBzNuVwVCnGBycA5NbdczfXEHixYtPs2uJNMkeQXd1CIzE3lOEe3kD
84b5hwO3BxmgDDgvreK71C18B6JHd6l58kN3qV0WWGF9+9g0jZaQAu52pkAjtkZ3/D0EujXH9l6j
qeoanqtzF9rnuJY2EAI2oQmBsQZ52A56mt+CCG1t47e3iSKGNQiRoMKoHQAdhUA06FdXfUg8/ntA
ICvnN5e0MWzszt3ZPXGcUAO1FLyTTrhNPmigvGjIhlmQuitjgkAjIqdA4jUSMrPgbiowCfYZOPzp
1FAEbW8LzrO0SGZFKLJtG5VOMgHqAcD8hWDb2GpaLqWmw27z6lp3lfZna4ZWmgPzMZWlY7nBwi7Q
PQ9sV0VFABRWT4f/ALTFncrqvnGZbycRPL5eXh3nyyAnAG3A5545rWoAKKKKACiiigAooooAKKKK
ACiiigAooooAKKKKACo52lS3leCMSyqhKRltoZscDPOMnvUlFAGbaW11PcWup3cs9tObQRy6esoe
FHJDE5xywI25zjHatIADoMUUUAFFFFABRRRQAUUUUAVIbSaLUrq6e+nlhmVAlswXZCVzkrgZ+bPO
SelW6KKACiqllNezPdi8s0t1jnKQFZt/mx4GHPA2kkkY9qt0AFFFFABRRRQAUUUUAFFFFABRRRQA
UUUUAFFFFABRRRQAUUUUAFFFFABRRRQAUUUUAFFFFABRRRQAUUUUAFFFFAH/2Q==</Data></Thumbnail></Binary><mdChar><CharSetCd value="004" Sync="TRUE"></CharSetCd></mdChar></metadata>
